charts/__init__.py
charts/chart.py
charts/core.py
charts/data.py
charts/index-async.html
charts/index.html
charts/jsonencoder.py
charts/options.py
charts/plot.py
charts/server.py
charts/settings.py
charts-0.4.6.dist-info/DESCRIPTION.rst
charts-0.4.6.dist-info/METADATA
charts-0.4.6.dist-info/metadata.json
charts-0.4.6.dist-info/RECORD
charts-0.4.6.dist-info/top_level.txt
charts-0.4.6.dist-info/WHEEL
